snapshot_pkg/__init__.py
snapshot_pkg/__main__.py
snapshot_pkg/restore.py
snapshot_pkg/snapshot.py
snapshot_pkg/utils.py
snapshot_pkg-0.1.0.dist-info/LICENSE
snapshot_pkg-0.1.0.dist-info/METADATA
snapshot_pkg-0.1.0.dist-info/WHEEL
snapshot_pkg-0.1.0.dist-info/entry_points.txt
snapshot_pkg-0.1.0.dist-info/top_level.txt
snapshot_pkg-0.1.0.dist-info/RECORD
