Metadata-Version: 2.2
Name: snapshot_pkg
Version: 0.1.0
Summary: A utility to create, manage, and restore snapshots of Python packages and directory structures
Home-page: https://github.com/B4PT0R/snapshot_pkg
Author: Baptiste FERRAND
Author-email: bferrand.maths@gmail.com
Project-URL: Bug Reports, https://github.com/B4PT0R/snapshot_pkg/issues
Project-URL: Source, https://github.com/B4PT0R/snapshot_pkg
Keywords: snapshot,backup,restore,versioning,documentation,ai-collaboration,development-tools
Classifier: Programming Language :: Python :: 3
Classifier: License :: OSI Approved :: MIT License
Classifier: Operating System :: OS Independent
Classifier: Development Status :: 4 - Beta
Classifier: Intended Audience :: Developers
Classifier: Topic :: Software Development :: Libraries :: Python Modules
Requires-Python: >=3.6
License-File: LICENSE
Requires-Dist: pathspec
Dynamic: author
Dynamic: author-email
Dynamic: classifier
Dynamic: description
Dynamic: description-content-type
Dynamic: home-page
Dynamic: keywords
Dynamic: project-url
Dynamic: requires-dist
Dynamic: requires-python
Dynamic: summary
